client/__init__.py
client/client.py
client/client/__init__.py
client/client/add_contact.py
client/client/database.py
client/client/del_contact.py
client/client/main_window.py
client/client/main_window_conv.py
client/client/start_dialog.py
client/client/transport.py
client/client_data/__init__.py
client/client_data/add_contact.py
client/client_data/database.py
client/client_data/del_contact.py
client/client_data/main_window.py
client/client_data/main_window_conv.py
client/client_data/start_dialog.py
client/client_data/transport.py
client/common/__init__.py
client/common/decorator.py
client/common/descryptors.py
client/common/errors.py
client/common/metaclasses.py
client/common/utils.py
client/common/variables.py
client/logs/__init__.py
client/logs/client_log_config.py
client/logs/server_log_config.py
client/unit_test/__init__.py
mess_client_march-0.7.0.dist-info/METADATA
mess_client_march-0.7.0.dist-info/WHEEL
mess_client_march-0.7.0.dist-info/top_level.txt
mess_client_march-0.7.0.dist-info/RECORD
